pynarrator/__init__.py
pynarrator/chatgpt.py
pynarrator/clean_text.py
pynarrator/data.py
pynarrator/format_pct.py
pynarrator/format_text.py
pynarrator/get_frequency.py
pynarrator/narrate_descriptive.py
pynarrator/narrate_trend.py
pynarrator/pluralize.py
pynarrator/tags.py
pynarrator/text_helpers.py
pynarrator/trend_helpers.py
pynarrator/ytd.py
pynarrator-0.0.1.15.dist-info/LICENSE
pynarrator-0.0.1.15.dist-info/METADATA
pynarrator-0.0.1.15.dist-info/WHEEL
pynarrator-0.0.1.15.dist-info/top_level.txt
pynarrator-0.0.1.15.dist-info/RECORD
