Metadata-Version: 2.1
Name: pynarrator
Version: 0.0.1.15
Summary: Template-based NLG framework for creating text narratives out of data
Author: Denis Abdullin
Author-email: denisabdullincz@gmail.com
Keywords: python,nlg,template,chatgpt
Classifier: Intended Audience :: Developers
Classifier: Programming Language :: Python :: 3
Classifier: Programming Language :: Python :: 3.6
Classifier: Programming Language :: Python :: 3.7
Classifier: Programming Language :: Python :: 3.8
Classifier: Programming Language :: Python :: 3.9
Classifier: Programming Language :: Python :: 3.10
Classifier: Programming Language :: Python :: 3.11
Classifier: Operating System :: OS Independent
License-File: LICENSE
Requires-Dist: pandas (>=1.0.0)
Requires-Dist: inflect (>=6.0.0)
Requires-Dist: openai
Provides-Extra: dev
Requires-Dist: pytest (>=3.7) ; extra == 'dev'
